COPYING
COPYING.LESSER
MANIFEST.in
README.rst
setup.cfg
setup.py
versioneer.py
ext/bar/_bar.c
ext/bar/_bar.h
ext/bar/bar.c
ext/bar/bar.pyx
ext/dtram/_dtram.c
ext/dtram/_dtram.h
ext/dtram/dtram.c
ext/dtram/dtram.pyx
ext/mbar/_mbar.c
ext/mbar/_mbar.h
ext/mbar/mbar.c
ext/mbar/mbar.pyx
ext/mbar_direct/_mbar_direct.c
ext/mbar_direct/_mbar_direct.h
ext/mbar_direct/mbar_direct.c
ext/mbar_direct/mbar_direct.pyx
ext/tram/_tram.c
ext/tram/_tram.h
ext/tram/tram.c
ext/tram/tram.pyx
ext/tram_direct/_tram_direct.c
ext/tram_direct/_tram_direct.h
ext/tram_direct/tram_direct.c
ext/tram_direct/tram_direct.pyx
ext/trammbar/trammbar.c
ext/trammbar/trammbar.pyx
ext/trammbar_direct/trammbar_direct.c
ext/trammbar_direct/trammbar_direct.pyx
ext/util/_util.c
ext/util/_util.h
ext/util/util.c
ext/util/util.pyx
ext/wham/_wham.c
ext/wham/_wham.h
ext/wham/wham.c
ext/wham/wham.pyx
test/test_3_2_model.py
test/test_bar.py
test/test_callback.py
test/test_cset.py
test/test_dtram.py
test/test_mbar.py
test/test_random_model.py
test/test_util.py
test/test_wham.py
thermotools/__init__.py
thermotools/_version.py
thermotools/callback.py
thermotools/cset.py
thermotools.egg-info/PKG-INFO
thermotools.egg-info/SOURCES.txt
thermotools.egg-info/dependency_links.txt
thermotools.egg-info/requires.txt
thermotools.egg-info/top_level.txt